{
    "_declaration": {
        "_attributes": {
            "version": "1.0",
            "encoding": "UTF-8",
            "standalone": "yes"
        }
    },
    "w:document": {
        "_attributes": {
            "xmlns:wpc": "http://schemas.microsoft.com/office/word/2010/wordprocessingCanvas",
            "xmlns:cx": "http://schemas.microsoft.com/office/drawing/2014/chartex",
            "xmlns:cx1": "http://schemas.microsoft.com/office/drawing/2015/9/8/chartex",
            "xmlns:cx2": "http://schemas.microsoft.com/office/drawing/2015/10/21/chartex",
            "xmlns:cx3": "http://schemas.microsoft.com/office/drawing/2016/5/9/chartex",
            "xmlns:cx4": "http://schemas.microsoft.com/office/drawing/2016/5/10/chartex",
            "xmlns:cx5": "http://schemas.microsoft.com/office/drawing/2016/5/11/chartex",
            "xmlns:cx6": "http://schemas.microsoft.com/office/drawing/2016/5/12/chartex",
            "xmlns:cx7": "http://schemas.microsoft.com/office/drawing/2016/5/13/chartex",
            "xmlns:cx8": "http://schemas.microsoft.com/office/drawing/2016/5/14/chartex",
            "xmlns:mc": "http://schemas.openxmlformats.org/markup-compatibility/2006",
            "xmlns:aink": "http://schemas.microsoft.com/office/drawing/2016/ink",
            "xmlns:am3d": "http://schemas.microsoft.com/office/drawing/2017/model3d",
            "xmlns:o": "urn:schemas-microsoft-com:office:office",
            "xmlns:r": "http://schemas.openxmlformats.org/officeDocument/2006/relationships",
            "xmlns:m": "http://schemas.openxmlformats.org/officeDocument/2006/math",
            "xmlns:v": "urn:schemas-microsoft-com:vml",
            "xmlns:wp14": "http://schemas.microsoft.com/office/word/2010/wordprocessingDrawing",
            "xmlns:wp": "http://schemas.openxmlformats.org/drawingml/2006/wordprocessingDrawing",
            "xmlns:w10": "urn:schemas-microsoft-com:office:word",
            "xmlns:w": "http://schemas.openxmlformats.org/wordprocessingml/2006/main",
            "xmlns:w14": "http://schemas.microsoft.com/office/word/2010/wordml",
            "xmlns:w15": "http://schemas.microsoft.com/office/word/2012/wordml",
            "xmlns:w16cid": "http://schemas.microsoft.com/office/word/2016/wordml/cid",
            "xmlns:w16se": "http://schemas.microsoft.com/office/word/2015/wordml/symex",
            "xmlns:wpg": "http://schemas.microsoft.com/office/word/2010/wordprocessingGroup",
            "xmlns:wpi": "http://schemas.microsoft.com/office/word/2010/wordprocessingInk",
            "xmlns:wne": "http://schemas.microsoft.com/office/word/2006/wordml",
            "xmlns:wps": "http://schemas.microsoft.com/office/word/2010/wordprocessingShape",
            "mc:Ignorable": "w14 w15 w16se w16cid wp14"
        },
        "w:body": {
            "w:tbl": {
                "w:tblPr": {
                    "w:tblStyle": {
                        "_attributes": {
                            "w:val": "TableGrid"
                        }
                    },
                    "w:tblW": {
                        "_attributes": {
                            "w:w": "0",
                            "w:type": "auto"
                        }
                    },
                    "w:tblLook": {
                        "_attributes": {
                            "w:val": "04A0",
                            "w:firstRow": "1",
                            "w:lastRow": "0",
                            "w:firstColumn": "1",
                            "w:lastColumn": "0",
                            "w:noHBand": "0",
                            "w:noVBand": "1"
                        }
                    }
                },
                "w:tblGrid": {
                    "w:gridCol": [
                        {
                            "_attributes": {
                                "w:w": "935"
                            }
                        },
                        {
                            "_attributes": {
                                "w:w": "935"
                            }
                        },
                        {
                            "_attributes": {
                                "w:w": "935"
                            }
                        },
                        {
                            "_attributes": {
                                "w:w": "935"
                            }
                        },
                        {
                            "_attributes": {
                                "w:w": "935"
                            }
                        },
                        {
                            "_attributes": {
                                "w:w": "935"
                            }
                        },
                        {
                            "_attributes": {
                                "w:w": "935"
                            }
                        },
                        {
                            "_attributes": {
                                "w:w": "935"
                            }
                        },
                        {
                            "_attributes": {
                                "w:w": "935"
                            }
                        },
                        {
                            "_attributes": {
                                "w:w": "935"
                            }
                        }
                    ]
                },
                "w:tr": [
                    {
                        "_attributes": {
                            "w:rsidR": "009E50BE",
                            "w:rsidTr": "009E50BE"
                        },
                        "w:tc": [
                            {
                                "w:tcPr": {
                                    "w:tcW": {
                                        "_attributes": {
                                            "w:w": "935",
                                            "w:type": "dxa"
                                        }
                                    }
                                },
                                "w:p": {
                                    "_attributes": {
                                        "w:rsidR": "009E50BE",
                                        "w:rsidRDefault": "009E50BE"
                                    },
                                    "w:r": {
                                        "w:t": {
                                            "_text": "a"
                                        }
                                    }
                                }
                            },
                            {
                                "w:tcPr": {
                                    "w:tcW": {
                                        "_attributes": {
                                            "w:w": "935",
                                            "w:type": "dxa"
                                        }
                                    }
                                },
                                "w:p": {
                                    "_attributes": {
                                        "w:rsidR": "009E50BE",
                                        "w:rsidRDefault": "009E50BE"
                                    },
                                    "w:r": {
                                        "w:t": {
                                            "_text": "b"
                                        }
                                    }
                                }
                            },
                            {
                                "w:tcPr": {
                                    "w:tcW": {
                                        "_attributes": {
                                            "w:w": "935",
                                            "w:type": "dxa"
                                        }
                                    }
                                },
                                "w:p": {
                                    "_attributes": {
                                        "w:rsidR": "009E50BE",
                                        "w:rsidRDefault": "009E50BE"
                                    },
                                    "w:r": {
                                        "w:t": {
                                            "_text": "c"
                                        }
                                    }
                                }
                            },
                            {
                                "w:tcPr": {
                                    "w:tcW": {
                                        "_attributes": {
                                            "w:w": "935",
                                            "w:type": "dxa"
                                        }
                                    }
                                },
                                "w:p": {
                                    "_attributes": {
                                        "w:rsidR": "009E50BE",
                                        "w:rsidRDefault": "009E50BE"
                                    },
                                    "w:r": {
                                        "w:t": {
                                            "_text": "d"
                                        }
                                    }
                                }
                            },
                            {
                                "w:tcPr": {
                                    "w:tcW": {
                                        "_attributes": {
                                            "w:w": "935",
                                            "w:type": "dxa"
                                        }
                                    }
                                },
                                "w:p": {
                                    "_attributes": {
                                        "w:rsidR": "009E50BE",
                                        "w:rsidRDefault": "009E50BE"
                                    },
                                    "w:r": {
                                        "w:t": {
                                            "_text": "e"
                                        }
                                    }
                                }
                            },
                            {
                                "w:tcPr": {
                                    "w:tcW": {
                                        "_attributes": {
                                            "w:w": "935",
                                            "w:type": "dxa"
                                        }
                                    }
                                },
                                "w:p": {
                                    "_attributes": {
                                        "w:rsidR": "009E50BE",
                                        "w:rsidRDefault": "009E50BE"
                                    },
                                    "w:r": {
                                        "w:t": {
                                            "_text": "f"
                                        }
                                    }
                                }
                            },
                            {
                                "w:tcPr": {
                                    "w:tcW": {
                                        "_attributes": {
                                            "w:w": "935",
                                            "w:type": "dxa"
                                        }
                                    }
                                },
                                "w:p": {
                                    "_attributes": {
                                        "w:rsidR": "009E50BE",
                                        "w:rsidRDefault": "009E50BE"
                                    },
                                    "w:r": {
                                        "w:t": {
                                            "_text": "g"
                                        }
                                    }
                                }
                            },
                            {
                                "w:tcPr": {
                                    "w:tcW": {
                                        "_attributes": {
                                            "w:w": "935",
                                            "w:type": "dxa"
                                        }
                                    }
                                },
                                "w:p": {
                                    "_attributes": {
                                        "w:rsidR": "009E50BE",
                                        "w:rsidRDefault": "009E50BE"
                                    },
                                    "w:r": {
                                        "w:t": {
                                            "_text": "h"
                                        }
                                    }
                                }
                            },
                            {
                                "w:tcPr": {
                                    "w:tcW": {
                                        "_attributes": {
                                            "w:w": "935",
                                            "w:type": "dxa"
                                        }
                                    }
                                },
                                "w:p": {
                                    "_attributes": {
                                        "w:rsidR": "009E50BE",
                                        "w:rsidRDefault": "009E50BE"
                                    },
                                    "w:proofErr": [
                                        {
                                            "_attributes": {
                                                "w:type": "spellStart"
                                            }
                                        },
                                        {
                                            "_attributes": {
                                                "w:type": "spellEnd"
                                            }
                                        }
                                    ],
                                    "w:r": {
                                        "w:t": {
                                            "_text": "i"
                                        }
                                    }
                                }
                            },
                            {
                                "w:tcPr": {
                                    "w:tcW": {
                                        "_attributes": {
                                            "w:w": "935",
                                            "w:type": "dxa"
                                        }
                                    }
                                },
                                "w:p": {
                                    "_attributes": {
                                        "w:rsidR": "009E50BE",
                                        "w:rsidRDefault": "009E50BE"
                                    },
                                    "w:r": {
                                        "w:t": {
                                            "_text": "j"
                                        }
                                    }
                                }
                            }
                        ]
                    },
                    {
                        "_attributes": {
                            "w:rsidR": "009E50BE",
                            "w:rsidTr": "009E50BE"
                        },
                        "w:tc": [
                            {
                                "w:tcPr": {
                                    "w:tcW": {
                                        "_attributes": {
                                            "w:w": "935",
                                            "w:type": "dxa"
                                        }
                                    }
                                },
                                "w:p": {
                                    "_attributes": {
                                        "w:rsidR": "009E50BE",
                                        "w:rsidRDefault": "009E50BE"
                                    },
                                    "w:r": {
                                        "w:t": {
                                            "_text": "k"
                                        }
                                    }
                                }
                            },
                            {
                                "w:tcPr": {
                                    "w:tcW": {
                                        "_attributes": {
                                            "w:w": "935",
                                            "w:type": "dxa"
                                        }
                                    }
                                },
                                "w:p": {
                                    "_attributes": {
                                        "w:rsidR": "009E50BE",
                                        "w:rsidRDefault": "009E50BE"
                                    },
                                    "w:r": {
                                        "w:t": {
                                            "_text": "l"
                                        }
                                    }
                                }
                            },
                            {
                                "w:tcPr": {
                                    "w:tcW": {
                                        "_attributes": {
                                            "w:w": "935",
                                            "w:type": "dxa"
                                        }
                                    }
                                },
                                "w:p": {
                                    "_attributes": {
                                        "w:rsidR": "009E50BE",
                                        "w:rsidRDefault": "009E50BE"
                                    },
                                    "w:r": {
                                        "w:t": {
                                            "_text": "m"
                                        }
                                    }
                                }
                            },
                            {
                                "w:tcPr": {
                                    "w:tcW": {
                                        "_attributes": {
                                            "w:w": "935",
                                            "w:type": "dxa"
                                        }
                                    }
                                },
                                "w:p": {
                                    "_attributes": {
                                        "w:rsidR": "009E50BE",
                                        "w:rsidRDefault": "009E50BE"
                                    },
                                    "w:r": {
                                        "w:t": {
                                            "_text": "n"
                                        }
                                    }
                                }
                            },
                            {
                                "w:tcPr": {
                                    "w:tcW": {
                                        "_attributes": {
                                            "w:w": "935",
                                            "w:type": "dxa"
                                        }
                                    }
                                },
                                "w:p": {
                                    "_attributes": {
                                        "w:rsidR": "009E50BE",
                                        "w:rsidRDefault": "009E50BE"
                                    },
                                    "w:r": {
                                        "w:t": {
                                            "_text": "o"
                                        }
                                    }
                                }
                            },
                            {
                                "w:tcPr": {
                                    "w:tcW": {
                                        "_attributes": {
                                            "w:w": "935",
                                            "w:type": "dxa"
                                        }
                                    }
                                },
                                "w:p": {
                                    "_attributes": {
                                        "w:rsidR": "009E50BE",
                                        "w:rsidRDefault": "009E50BE"
                                    },
                                    "w:r": {
                                        "w:t": {
                                            "_text": "p"
                                        }
                                    }
                                }
                            },
                            {
                                "w:tcPr": {
                                    "w:tcW": {
                                        "_attributes": {
                                            "w:w": "935",
                                            "w:type": "dxa"
                                        }
                                    }
                                },
                                "w:p": {
                                    "_attributes": {
                                        "w:rsidR": "009E50BE",
                                        "w:rsidRDefault": "009E50BE"
                                    },
                                    "w:r": {
                                        "w:t": {
                                            "_text": "q"
                                        }
                                    }
                                }
                            },
                            {
                                "w:tcPr": {
                                    "w:tcW": {
                                        "_attributes": {
                                            "w:w": "935",
                                            "w:type": "dxa"
                                        }
                                    }
                                },
                                "w:p": {
                                    "_attributes": {
                                        "w:rsidR": "009E50BE",
                                        "w:rsidRDefault": "009E50BE"
                                    },
                                    "w:r": {
                                        "w:t": {
                                            "_text": "r"
                                        }
                                    }
                                }
                            },
                            {
                                "w:tcPr": {
                                    "w:tcW": {
                                        "_attributes": {
                                            "w:w": "935",
                                            "w:type": "dxa"
                                        }
                                    }
                                },
                                "w:p": {
                                    "_attributes": {
                                        "w:rsidR": "009E50BE",
                                        "w:rsidRDefault": "009E50BE"
                                    },
                                    "w:r": {
                                        "w:t": {
                                            "_text": "s"
                                        }
                                    }
                                }
                            },
                            {
                                "w:tcPr": {
                                    "w:tcW": {
                                        "_attributes": {
                                            "w:w": "935",
                                            "w:type": "dxa"
                                        }
                                    }
                                },
                                "w:p": {
                                    "_attributes": {
                                        "w:rsidR": "009E50BE",
                                        "w:rsidRDefault": "009E50BE"
                                    },
                                    "w:r": {
                                        "w:t": {
                                            "_text": "t"
                                        }
                                    }
                                }
                            }
                        ]
                    },
                    {
                        "_attributes": {
                            "w:rsidR": "009E50BE",
                            "w:rsidTr": "009E50BE"
                        },
                        "w:tc": [
                            {
                                "w:tcPr": {
                                    "w:tcW": {
                                        "_attributes": {
                                            "w:w": "935",
                                            "w:type": "dxa"
                                        }
                                    }
                                },
                                "w:p": {
                                    "_attributes": {
                                        "w:rsidR": "009E50BE",
                                        "w:rsidRDefault": "009E50BE"
                                    },
                                    "w:r": {
                                        "w:t": {
                                            "_text": "u"
                                        }
                                    }
                                }
                            },
                            {
                                "w:tcPr": {
                                    "w:tcW": {
                                        "_attributes": {
                                            "w:w": "935",
                                            "w:type": "dxa"
                                        }
                                    }
                                },
                                "w:p": {
                                    "_attributes": {
                                        "w:rsidR": "009E50BE",
                                        "w:rsidRDefault": "009E50BE"
                                    },
                                    "w:r": {
                                        "w:t": {
                                            "_text": "v"
                                        }
                                    }
                                }
                            },
                            {
                                "w:tcPr": {
                                    "w:tcW": {
                                        "_attributes": {
                                            "w:w": "935",
                                            "w:type": "dxa"
                                        }
                                    }
                                },
                                "w:p": {
                                    "_attributes": {
                                        "w:rsidR": "009E50BE",
                                        "w:rsidRDefault": "009E50BE"
                                    },
                                    "w:r": {
                                        "w:t": {
                                            "_text": "w"
                                        }
                                    }
                                }
                            },
                            {
                                "w:tcPr": {
                                    "w:tcW": {
                                        "_attributes": {
                                            "w:w": "935",
                                            "w:type": "dxa"
                                        }
                                    }
                                },
                                "w:p": {
                                    "_attributes": {
                                        "w:rsidR": "009E50BE",
                                        "w:rsidRDefault": "009E50BE"
                                    },
                                    "w:r": {
                                        "w:t": {
                                            "_text": "x"
                                        }
                                    }
                                }
                            },
                            {
                                "w:tcPr": {
                                    "w:tcW": {
                                        "_attributes": {
                                            "w:w": "935",
                                            "w:type": "dxa"
                                        }
                                    }
                                },
                                "w:p": {
                                    "_attributes": {
                                        "w:rsidR": "009E50BE",
                                        "w:rsidRDefault": "009E50BE"
                                    },
                                    "w:r": {
                                        "w:t": {
                                            "_text": "y"
                                        }
                                    }
                                }
                            },
                            {
                                "w:tcPr": {
                                    "w:tcW": {
                                        "_attributes": {
                                            "w:w": "935",
                                            "w:type": "dxa"
                                        }
                                    }
                                },
                                "w:p": {
                                    "_attributes": {
                                        "w:rsidR": "009E50BE",
                                        "w:rsidRDefault": "009E50BE"
                                    },
                                    "w:r": {
                                        "w:t": {
                                            "_text": "z"
                                        }
                                    }
                                }
                            },
                            {
                                "w:tcPr": {
                                    "w:tcW": {
                                        "_attributes": {
                                            "w:w": "935",
                                            "w:type": "dxa"
                                        }
                                    }
                                },
                                "w:p": {
                                    "_attributes": {
                                        "w:rsidR": "009E50BE",
                                        "w:rsidRDefault": "009E50BE"
                                    },
                                    "w:r": {
                                        "w:t": {
                                            "_text": "1"
                                        }
                                    }
                                }
                            },
                            {
                                "w:tcPr": {
                                    "w:tcW": {
                                        "_attributes": {
                                            "w:w": "935",
                                            "w:type": "dxa"
                                        }
                                    }
                                },
                                "w:p": {
                                    "_attributes": {
                                        "w:rsidR": "009E50BE",
                                        "w:rsidRDefault": "009E50BE"
                                    },
                                    "w:r": {
                                        "w:t": {
                                            "_text": "2"
                                        }
                                    }
                                }
                            },
                            {
                                "w:tcPr": {
                                    "w:tcW": {
                                        "_attributes": {
                                            "w:w": "935",
                                            "w:type": "dxa"
                                        }
                                    }
                                },
                                "w:p": {
                                    "_attributes": {
                                        "w:rsidR": "009E50BE",
                                        "w:rsidRDefault": "009E50BE"
                                    },
                                    "w:r": {
                                        "w:t": {
                                            "_text": "3"
                                        }
                                    }
                                }
                            },
                            {
                                "w:tcPr": {
                                    "w:tcW": {
                                        "_attributes": {
                                            "w:w": "935",
                                            "w:type": "dxa"
                                        }
                                    }
                                },
                                "w:p": {
                                    "_attributes": {
                                        "w:rsidR": "009E50BE",
                                        "w:rsidRDefault": "009E50BE"
                                    },
                                    "w:r": {
                                        "w:t": {
                                            "_text": "4"
                                        }
                                    }
                                }
                            }
                        ]
                    },
                    {
                        "_attributes": {
                            "w:rsidR": "009E50BE",
                            "w:rsidTr": "009E50BE"
                        },
                        "w:tc": [
                            {
                                "w:tcPr": {
                                    "w:tcW": {
                                        "_attributes": {
                                            "w:w": "935",
                                            "w:type": "dxa"
                                        }
                                    }
                                },
                                "w:p": {
                                    "_attributes": {
                                        "w:rsidR": "009E50BE",
                                        "w:rsidRDefault": "009E50BE"
                                    },
                                    "w:r": {
                                        "w:t": {
                                            "_text": "5"
                                        }
                                    }
                                }
                            },
                            {
                                "w:tcPr": {
                                    "w:tcW": {
                                        "_attributes": {
                                            "w:w": "935",
                                            "w:type": "dxa"
                                        }
                                    }
                                },
                                "w:p": {
                                    "_attributes": {
                                        "w:rsidR": "009E50BE",
                                        "w:rsidRDefault": "009E50BE"
                                    },
                                    "w:r": {
                                        "w:t": {
                                            "_text": "6"
                                        }
                                    }
                                }
                            },
                            {
                                "w:tcPr": {
                                    "w:tcW": {
                                        "_attributes": {
                                            "w:w": "935",
                                            "w:type": "dxa"
                                        }
                                    }
                                },
                                "w:p": {
                                    "_attributes": {
                                        "w:rsidR": "009E50BE",
                                        "w:rsidRDefault": "009E50BE"
                                    },
                                    "w:r": {
                                        "w:t": {
                                            "_text": "7"
                                        }
                                    }
                                }
                            },
                            {
                                "w:tcPr": {
                                    "w:tcW": {
                                        "_attributes": {
                                            "w:w": "935",
                                            "w:type": "dxa"
                                        }
                                    }
                                },
                                "w:p": {
                                    "_attributes": {
                                        "w:rsidR": "009E50BE",
                                        "w:rsidRDefault": "009E50BE"
                                    },
                                    "w:r": {
                                        "w:t": {
                                            "_text": "8"
                                        }
                                    }
                                }
                            },
                            {
                                "w:tcPr": {
                                    "w:tcW": {
                                        "_attributes": {
                                            "w:w": "935",
                                            "w:type": "dxa"
                                        }
                                    }
                                },
                                "w:p": {
                                    "_attributes": {
                                        "w:rsidR": "009E50BE",
                                        "w:rsidRDefault": "009E50BE"
                                    },
                                    "w:r": {
                                        "w:t": {
                                            "_text": "9"
                                        }
                                    }
                                }
                            },
                            {
                                "w:tcPr": {
                                    "w:tcW": {
                                        "_attributes": {
                                            "w:w": "935",
                                            "w:type": "dxa"
                                        }
                                    }
                                },
                                "w:p": {
                                    "_attributes": {
                                        "w:rsidR": "009E50BE",
                                        "w:rsidRDefault": "009E50BE"
                                    },
                                    "w:r": {
                                        "w:t": {
                                            "_text": "10"
                                        }
                                    }
                                }
                            },
                            {
                                "w:tcPr": {
                                    "w:tcW": {
                                        "_attributes": {
                                            "w:w": "935",
                                            "w:type": "dxa"
                                        }
                                    }
                                },
                                "w:p": {
                                    "_attributes": {
                                        "w:rsidR": "009E50BE",
                                        "w:rsidRDefault": "009E50BE"
                                    },
                                    "w:r": {
                                        "w:t": {
                                            "_text": "11"
                                        }
                                    }
                                }
                            },
                            {
                                "w:tcPr": {
                                    "w:tcW": {
                                        "_attributes": {
                                            "w:w": "935",
                                            "w:type": "dxa"
                                        }
                                    }
                                },
                                "w:p": {
                                    "_attributes": {
                                        "w:rsidR": "009E50BE",
                                        "w:rsidRDefault": "009E50BE"
                                    },
                                    "w:r": {
                                        "w:t": {
                                            "_text": "12"
                                        }
                                    }
                                }
                            },
                            {
                                "w:tcPr": {
                                    "w:tcW": {
                                        "_attributes": {
                                            "w:w": "935",
                                            "w:type": "dxa"
                                        }
                                    }
                                },
                                "w:p": {
                                    "_attributes": {
                                        "w:rsidR": "009E50BE",
                                        "w:rsidRDefault": "009E50BE"
                                    },
                                    "w:r": {
                                        "w:t": {
                                            "_text": "13"
                                        }
                                    }
                                }
                            },
                            {
                                "w:tcPr": {
                                    "w:tcW": {
                                        "_attributes": {
                                            "w:w": "935",
                                            "w:type": "dxa"
                                        }
                                    }
                                },
                                "w:p": {
                                    "_attributes": {
                                        "w:rsidR": "009E50BE",
                                        "w:rsidRDefault": "009E50BE"
                                    },
                                    "w:r": {
                                        "w:t": {
                                            "_text": "14"
                                        }
                                    }
                                }
                            }
                        ]
                    },
                    {
                        "_attributes": {
                            "w:rsidR": "009E50BE",
                            "w:rsidTr": "009E50BE"
                        },
                        "w:tc": [
                            {
                                "w:tcPr": {
                                    "w:tcW": {
                                        "_attributes": {
                                            "w:w": "935",
                                            "w:type": "dxa"
                                        }
                                    }
                                },
                                "w:p": {
                                    "_attributes": {
                                        "w:rsidR": "009E50BE",
                                        "w:rsidRDefault": "009E50BE"
                                    },
                                    "w:r": {
                                        "w:t": {
                                            "_text": "15"
                                        }
                                    }
                                }
                            },
                            {
                                "w:tcPr": {
                                    "w:tcW": {
                                        "_attributes": {
                                            "w:w": "935",
                                            "w:type": "dxa"
                                        }
                                    }
                                },
                                "w:p": {
                                    "_attributes": {
                                        "w:rsidR": "009E50BE",
                                        "w:rsidRDefault": "009E50BE"
                                    },
                                    "w:r": {
                                        "w:t": {
                                            "_text": "16"
                                        }
                                    }
                                }
                            },
                            {
                                "w:tcPr": {
                                    "w:tcW": {
                                        "_attributes": {
                                            "w:w": "935",
                                            "w:type": "dxa"
                                        }
                                    }
                                },
                                "w:p": {
                                    "_attributes": {
                                        "w:rsidR": "009E50BE",
                                        "w:rsidRDefault": "009E50BE"
                                    },
                                    "w:r": {
                                        "w:t": {
                                            "_text": "17"
                                        }
                                    }
                                }
                            },
                            {
                                "w:tcPr": {
                                    "w:tcW": {
                                        "_attributes": {
                                            "w:w": "935",
                                            "w:type": "dxa"
                                        }
                                    }
                                },
                                "w:p": {
                                    "_attributes": {
                                        "w:rsidR": "009E50BE",
                                        "w:rsidRDefault": "009E50BE"
                                    },
                                    "w:r": {
                                        "w:t": {
                                            "_text": "18"
                                        }
                                    }
                                }
                            },
                            {
                                "w:tcPr": {
                                    "w:tcW": {
                                        "_attributes": {
                                            "w:w": "935",
                                            "w:type": "dxa"
                                        }
                                    }
                                },
                                "w:p": {
                                    "_attributes": {
                                        "w:rsidR": "009E50BE",
                                        "w:rsidRDefault": "009E50BE"
                                    },
                                    "w:r": {
                                        "w:t": {
                                            "_text": "19"
                                        }
                                    }
                                }
                            },
                            {
                                "w:tcPr": {
                                    "w:tcW": {
                                        "_attributes": {
                                            "w:w": "935",
                                            "w:type": "dxa"
                                        }
                                    }
                                },
                                "w:p": {
                                    "_attributes": {
                                        "w:rsidR": "009E50BE",
                                        "w:rsidRDefault": "009E50BE"
                                    },
                                    "w:r": {
                                        "w:t": {
                                            "_text": "20"
                                        }
                                    }
                                }
                            },
                            {
                                "w:tcPr": {
                                    "w:tcW": {
                                        "_attributes": {
                                            "w:w": "935",
                                            "w:type": "dxa"
                                        }
                                    }
                                },
                                "w:p": {
                                    "_attributes": {
                                        "w:rsidR": "009E50BE",
                                        "w:rsidRDefault": "009E50BE"
                                    },
                                    "w:r": {
                                        "w:t": {
                                            "_text": "21"
                                        }
                                    }
                                }
                            },
                            {
                                "w:tcPr": {
                                    "w:tcW": {
                                        "_attributes": {
                                            "w:w": "935",
                                            "w:type": "dxa"
                                        }
                                    }
                                },
                                "w:p": {
                                    "_attributes": {
                                        "w:rsidR": "009E50BE",
                                        "w:rsidRDefault": "009E50BE"
                                    },
                                    "w:r": {
                                        "w:t": {
                                            "_text": "22"
                                        }
                                    }
                                }
                            },
                            {
                                "w:tcPr": {
                                    "w:tcW": {
                                        "_attributes": {
                                            "w:w": "935",
                                            "w:type": "dxa"
                                        }
                                    }
                                },
                                "w:p": {
                                    "_attributes": {
                                        "w:rsidR": "009E50BE",
                                        "w:rsidRDefault": "009E50BE"
                                    },
                                    "w:r": {
                                        "w:t": {
                                            "_text": "23"
                                        }
                                    }
                                }
                            },
                            {
                                "w:tcPr": {
                                    "w:tcW": {
                                        "_attributes": {
                                            "w:w": "935",
                                            "w:type": "dxa"
                                        }
                                    }
                                },
                                "w:p": {
                                    "_attributes": {
                                        "w:rsidR": "009E50BE",
                                        "w:rsidRDefault": "009E50BE"
                                    },
                                    "w:r": {
                                        "w:t": {
                                            "_text": "24"
                                        }
                                    }
                                }
                            }
                        ]
                    },
                    {
                        "_attributes": {
                            "w:rsidR": "009E50BE",
                            "w:rsidTr": "009E50BE"
                        },
                        "w:tc": [
                            {
                                "w:tcPr": {
                                    "w:tcW": {
                                        "_attributes": {
                                            "w:w": "935",
                                            "w:type": "dxa"
                                        }
                                    }
                                },
                                "w:p": {
                                    "_attributes": {
                                        "w:rsidR": "009E50BE",
                                        "w:rsidRDefault": "009E50BE"
                                    },
                                    "w:r": {
                                        "w:t": {
                                            "_text": "25"
                                        }
                                    }
                                }
                            },
                            {
                                "w:tcPr": {
                                    "w:tcW": {
                                        "_attributes": {
                                            "w:w": "935",
                                            "w:type": "dxa"
                                        }
                                    }
                                },
                                "w:p": {
                                    "_attributes": {
                                        "w:rsidR": "009E50BE",
                                        "w:rsidRDefault": "009E50BE"
                                    },
                                    "w:r": {
                                        "w:t": {
                                            "_text": "26"
                                        }
                                    }
                                }
                            },
                            {
                                "w:tcPr": {
                                    "w:tcW": {
                                        "_attributes": {
                                            "w:w": "935",
                                            "w:type": "dxa"
                                        }
                                    }
                                },
                                "w:p": {
                                    "_attributes": {
                                        "w:rsidR": "009E50BE",
                                        "w:rsidRDefault": "009E50BE"
                                    },
                                    "w:r": {
                                        "w:t": {
                                            "_text": "27"
                                        }
                                    }
                                }
                            },
                            {
                                "w:tcPr": {
                                    "w:tcW": {
                                        "_attributes": {
                                            "w:w": "935",
                                            "w:type": "dxa"
                                        }
                                    }
                                },
                                "w:p": {
                                    "_attributes": {
                                        "w:rsidR": "009E50BE",
                                        "w:rsidRDefault": "009E50BE"
                                    },
                                    "w:r": {
                                        "w:t": {
                                            "_text": "28"
                                        }
                                    }
                                }
                            },
                            {
                                "w:tcPr": {
                                    "w:tcW": {
                                        "_attributes": {
                                            "w:w": "935",
                                            "w:type": "dxa"
                                        }
                                    }
                                },
                                "w:p": {
                                    "_attributes": {
                                        "w:rsidR": "009E50BE",
                                        "w:rsidRDefault": "009E50BE"
                                    },
                                    "w:r": {
                                        "w:t": {
                                            "_text": "29"
                                        }
                                    }
                                }
                            },
                            {
                                "w:tcPr": {
                                    "w:tcW": {
                                        "_attributes": {
                                            "w:w": "935",
                                            "w:type": "dxa"
                                        }
                                    }
                                },
                                "w:p": {
                                    "_attributes": {
                                        "w:rsidR": "009E50BE",
                                        "w:rsidRDefault": "009E50BE"
                                    },
                                    "w:r": {
                                        "w:t": {
                                            "_text": "30"
                                        }
                                    }
                                }
                            },
                            {
                                "w:tcPr": {
                                    "w:tcW": {
                                        "_attributes": {
                                            "w:w": "935",
                                            "w:type": "dxa"
                                        }
                                    }
                                },
                                "w:p": {
                                    "_attributes": {
                                        "w:rsidR": "009E50BE",
                                        "w:rsidRDefault": "009E50BE"
                                    },
                                    "w:r": {
                                        "w:t": {
                                            "_text": "31"
                                        }
                                    }
                                }
                            },
                            {
                                "w:tcPr": {
                                    "w:tcW": {
                                        "_attributes": {
                                            "w:w": "935",
                                            "w:type": "dxa"
                                        }
                                    }
                                },
                                "w:p": {
                                    "_attributes": {
                                        "w:rsidR": "009E50BE",
                                        "w:rsidRDefault": "009E50BE"
                                    },
                                    "w:r": {
                                        "w:t": {
                                            "_text": "32"
                                        }
                                    }
                                }
                            },
                            {
                                "w:tcPr": {
                                    "w:tcW": {
                                        "_attributes": {
                                            "w:w": "935",
                                            "w:type": "dxa"
                                        }
                                    }
                                },
                                "w:p": {
                                    "_attributes": {
                                        "w:rsidR": "009E50BE",
                                        "w:rsidRDefault": "009E50BE"
                                    },
                                    "w:r": {
                                        "w:t": {
                                            "_text": "33"
                                        }
                                    }
                                }
                            },
                            {
                                "w:tcPr": {
                                    "w:tcW": {
                                        "_attributes": {
                                            "w:w": "935",
                                            "w:type": "dxa"
                                        }
                                    }
                                },
                                "w:p": {
                                    "_attributes": {
                                        "w:rsidR": "009E50BE",
                                        "w:rsidRDefault": "009E50BE"
                                    },
                                    "w:r": {
                                        "w:t": {
                                            "_text": "34"
                                        }
                                    }
                                }
                            }
                        ]
                    },
                    {
                        "_attributes": {
                            "w:rsidR": "009E50BE",
                            "w:rsidTr": "009E50BE"
                        },
                        "w:tc": [
                            {
                                "w:tcPr": {
                                    "w:tcW": {
                                        "_attributes": {
                                            "w:w": "935",
                                            "w:type": "dxa"
                                        }
                                    }
                                },
                                "w:p": {
                                    "_attributes": {
                                        "w:rsidR": "009E50BE",
                                        "w:rsidRDefault": "009E50BE"
                                    },
                                    "w:r": {
                                        "w:t": {
                                            "_text": "35"
                                        }
                                    }
                                }
                            },
                            {
                                "w:tcPr": {
                                    "w:tcW": {
                                        "_attributes": {
                                            "w:w": "935",
                                            "w:type": "dxa"
                                        }
                                    }
                                },
                                "w:p": {
                                    "_attributes": {
                                        "w:rsidR": "009E50BE",
                                        "w:rsidRDefault": "009E50BE"
                                    },
                                    "w:r": {
                                        "w:t": {
                                            "_text": "36"
                                        }
                                    }
                                }
                            },
                            {
                                "w:tcPr": {
                                    "w:tcW": {
                                        "_attributes": {
                                            "w:w": "935",
                                            "w:type": "dxa"
                                        }
                                    }
                                },
                                "w:p": {
                                    "_attributes": {
                                        "w:rsidR": "009E50BE",
                                        "w:rsidRDefault": "009E50BE"
                                    },
                                    "w:r": {
                                        "w:t": {
                                            "_text": "37"
                                        }
                                    }
                                }
                            },
                            {
                                "w:tcPr": {
                                    "w:tcW": {
                                        "_attributes": {
                                            "w:w": "935",
                                            "w:type": "dxa"
                                        }
                                    }
                                },
                                "w:p": {
                                    "_attributes": {
                                        "w:rsidR": "009E50BE",
                                        "w:rsidRDefault": "009E50BE"
                                    },
                                    "w:r": {
                                        "w:t": {
                                            "_text": "38"
                                        }
                                    }
                                }
                            },
                            {
                                "w:tcPr": {
                                    "w:tcW": {
                                        "_attributes": {
                                            "w:w": "935",
                                            "w:type": "dxa"
                                        }
                                    }
                                },
                                "w:p": {
                                    "_attributes": {
                                        "w:rsidR": "009E50BE",
                                        "w:rsidRDefault": "009E50BE"
                                    },
                                    "w:r": {
                                        "w:t": {
                                            "_text": "39"
                                        }
                                    }
                                }
                            },
                            {
                                "w:tcPr": {
                                    "w:tcW": {
                                        "_attributes": {
                                            "w:w": "935",
                                            "w:type": "dxa"
                                        }
                                    }
                                },
                                "w:p": {
                                    "_attributes": {
                                        "w:rsidR": "009E50BE",
                                        "w:rsidRDefault": "009E50BE"
                                    },
                                    "w:r": {
                                        "w:t": {
                                            "_text": "40"
                                        }
                                    }
                                }
                            },
                            {
                                "w:tcPr": {
                                    "w:tcW": {
                                        "_attributes": {
                                            "w:w": "935",
                                            "w:type": "dxa"
                                        }
                                    }
                                },
                                "w:p": {
                                    "_attributes": {
                                        "w:rsidR": "009E50BE",
                                        "w:rsidRDefault": "009E50BE"
                                    },
                                    "w:r": {
                                        "w:t": {
                                            "_text": "41"
                                        }
                                    }
                                }
                            },
                            {
                                "w:tcPr": {
                                    "w:tcW": {
                                        "_attributes": {
                                            "w:w": "935",
                                            "w:type": "dxa"
                                        }
                                    }
                                },
                                "w:p": {
                                    "_attributes": {
                                        "w:rsidR": "009E50BE",
                                        "w:rsidRDefault": "009E50BE"
                                    },
                                    "w:r": {
                                        "w:t": {
                                            "_text": "42"
                                        }
                                    }
                                }
                            },
                            {
                                "w:tcPr": {
                                    "w:tcW": {
                                        "_attributes": {
                                            "w:w": "935",
                                            "w:type": "dxa"
                                        }
                                    }
                                },
                                "w:p": {
                                    "_attributes": {
                                        "w:rsidR": "009E50BE",
                                        "w:rsidRDefault": "009E50BE"
                                    },
                                    "w:r": {
                                        "w:t": {
                                            "_text": "43"
                                        }
                                    }
                                }
                            },
                            {
                                "w:tcPr": {
                                    "w:tcW": {
                                        "_attributes": {
                                            "w:w": "935",
                                            "w:type": "dxa"
                                        }
                                    }
                                },
                                "w:p": {
                                    "_attributes": {
                                        "w:rsidR": "009E50BE",
                                        "w:rsidRDefault": "009E50BE"
                                    },
                                    "w:r": {
                                        "w:t": {
                                            "_text": "44"
                                        }
                                    }
                                }
                            }
                        ]
                    }
                ]
            },
            "w:p": {
                "_attributes": {
                    "w:rsidR": "00D40923",
                    "w:rsidRDefault": "00D40923"
                },
                "w:bookmarkStart": {
                    "_attributes": {
                        "w:id": "0",
                        "w:name": "_GoBack"
                    }
                },
                "w:bookmarkEnd": {
                    "_attributes": {
                        "w:id": "0"
                    }
                }
            },
            "w:sectPr": {
                "_attributes": {
                    "w:rsidR": "00D40923"
                },
                "w:pgSz": {
                    "_attributes": {
                        "w:w": "12240",
                        "w:h": "15840"
                    }
                },
                "w:pgMar": {
                    "_attributes": {
                        "w:top": "1440",
                        "w:right": "1440",
                        "w:bottom": "1440",
                        "w:left": "1440",
                        "w:header": "720",
                        "w:footer": "720",
                        "w:gutter": "0"
                    }
                },
                "w:cols": {
                    "_attributes": {
                        "w:space": "720"
                    }
                },
                "w:docGrid": {
                    "_attributes": {
                        "w:linePitch": "360"
                    }
                }
            }
        }
    }
}
